{
    "games": [
        {
            "name":"friday_night_funkin",
            "fName":"Friday Night Funkin",
            "description":"Sigma rhythm game where you vibe with ur gf",
            "image":"/assets/images/game_covers/fnf.jpg",
            "online":true,
            "links":[
                {
                    "name":"FNFPorted",
                    "link":"https://jaguarkid817.github.io/fnf/"
                }
            ],
            "tags": [
            ]
        },
        {
            "name":"fnf_tricky",
            "fName":"The Tricky Mod",
            "description":"The tricky mod for my bros",
            "image":"/assets/images/game_covers/tricky.png",
            "online":true,
            "links":[
                {
                    "name":"FNFPorted",
                    "link":"https://jaguarkid817.github.io/tricky/"
                }
            ],
            "tags": [
            ]
        }
    ]
}
